{"months":{"format":{"abbreviated":["Yen","Fur","Meɣ","Yeb","May","Yun","Yul","Ɣuc","Cte","Tub","Nun","Duǧ"],"narrow":["Y","F","M","Y","M","Y","Y","Ɣ","C","T","N","D"],"short":null,"wide":["Yennayer","Fuṛar","Meɣres","Yebrir","Mayyu","Yunyu","Yulyu","Ɣuct","Ctembeṛ","Tubeṛ","Nunembeṛ","Duǧembeṛ"]},"stand_alone":null},"weekdays":{"format":{"abbreviated":["Yan","San","Kraḍ","Kuẓ","Sam","Sḍis","Say"],"narrow":["Y","S","K","K","S","S","S"],"short":["Yan","San","Kraḍ","Kuẓ","Sam","Sḍis","Say"],"wide":["Yanass","Sanass","Kraḍass","Kuẓass","Samass","Sḍisass","Sayass"]},"stand_alone":null},"day_periods":{"format":{"abbreviated":{"am":"n tufat","pm":"n tmeddit","noon":null,"midnight":null},"narrow":{"am":"n tufat","pm":"n tmeddit","noon":null,"midnight":null},"short":null,"wide":{"am":"n tufat","pm":"n tmeddit","noon":null,"midnight":null}},"stand_alone":null}}
