{"months":{"format":{"abbreviated":["rêb","reş","ada","avr","gul","pûş","tîr","gel","rez","kew","ser","ber"],"narrow":["R","R","A","A","G","P","T","G","R","K","S","B"],"short":null,"wide":["rêbendanê","reşemiyê","adarê","avrêlê","gulanê","pûşperê","tîrmehê","gelawêjê","rezberê","kewçêrê","sermawezê","berfanbarê"]},"stand_alone":{"abbreviated":null,"narrow":null,"short":null,"wide":["rêbendan","reşemî","adar","avrêl","gulan","pûşper","tîrmeh","gelawêj","rezber","kewçêr","sermawez","berfanbar"]}},"weekdays":{"format":{"abbreviated":["yş","dş","sş","çş","pş","în","ş"],"narrow":["Y","D","S","Ç","P","Î","Ş"],"short":["yş","dş","sş","çş","pş","în","ş"],"wide":["yekşem","duşem","sêşem","çarşem","pêncşem","în","şemî"]},"stand_alone":null},"day_periods":{"format":{"abbreviated":{"am":"BN","pm":"PN","noon":null,"midnight":null},"narrow":{"am":"BN","pm":"PN","noon":null,"midnight":null},"short":null,"wide":{"am":"BN","pm":"PN","noon":null,"midnight":null}},"stand_alone":null}}
