{"months":{"format":{"abbreviated":["ꖨꖕꔞ","ꕒꕡ","ꕾꖺ","ꖢꖕ","ꖑꕱ","ꖱꘋ","ꖱꕞ","ꗛꔕ","ꕢꕌ","ꕭꖃ","ꔞꘋ","ꖨꖕꗏ"],"narrow":["1","2","3","4","5","6","7","8","9","10","11","12"],"short":null,"wide":["ꖨꖕ ꕪꕴ ꔞꔀꕮꕊ","ꕒꕡꖝꖕ","ꕾꖺ","ꖢꖕ","ꖑꕱ","ꖱꘋ","ꖱꕞꔤ","ꗛꔕ","ꕢꕌ","ꕭꖃ","ꔞꘋꕔꕿ ꕸꖃꗏ","ꖨꖕ ꕪꕴ ꗏꖺꕮꕊ"]},"stand_alone":null},"weekdays":{"format":{"abbreviated":["ꕞꕌꔵ","ꗳꗡꘉ","ꕚꕞꕚ","ꕉꕞꕒ","ꕉꔤꕆꕢ","ꕉꔤꕀꕮ","ꔻꔬꔳ"],"narrow":["S","M","T","W","T","F","S"],"short":["ꕞꕌꔵ","ꗳꗡꘉ","ꕚꕞꕚ","ꕉꕞꕒ","ꕉꔤꕆꕢ","ꕉꔤꕀꕮ","ꔻꔬꔳ"],"wide":["ꕞꕌꔵ","ꗳꗡꘉ","ꕚꕞꕚ","ꕉꕞꕒ","ꕉꔤꕆꕢ","ꕉꔤꕀꕮ","ꔻꔬꔳ"]},"stand_alone":null},"day_periods":{"format":{"abbreviated":{"am":"AM","pm":"PM","noon":null,"midnight":null},"narrow":{"am":"AM","pm":"PM","noon":null,"midnight":null},"short":null,"wide":{"am":"AM","pm":"PM","noon":null,"midnight":null}},"stand_alone":null}}
