{"Afghanistan":"ម៉ោង​នៅ​អាហ្វហ្គានីស្ថាន","Africa_Central":"ម៉ោង​នៅ​អាហ្វ្រិក​កណ្ដាល","Africa_Eastern":"ម៉ោង​នៅ​អាហ្វ្រិក​ខាង​កើត","Africa_Southern":"ម៉ោង​នៅ​អាហ្វ្រិក​ខាង​ត្បូង","Africa_Western":"ម៉ោង​នៅ​អាហ្វ្រិក​ខាង​លិច","Alaska":"ម៉ោង​នៅ​អាឡាស្កា","Amazon":"ម៉ោង​នៅ​អាម៉ាហ្សូន","America_Central":"ម៉ោង​​នៅ​ទ្វីបអាមេរិក​ខាង​ជើងភាគកណ្តាល","America_Eastern":"ម៉ោងនៅទ្វីបអាមរិកខាងជើងភាគខាងកើត","America_Mountain":"ម៉ោង​នៅតំបន់ភ្នំនៃទ្វីប​អាមេរិក​​​ខាង​ជើង","America_Pacific":"ម៉ោងនៅប៉ាស៊ីហ្វិកអាមេរិក","Apia":"ម៉ោង​នៅ​អាប្យា","Arabian":"ម៉ោង​នៅ​អារ៉ាប់","Argentina":"ម៉ោង​នៅ​អាហ្សង់ទីន","Argentina_Western":"ម៉ោង​នៅ​អាហ្សង់ទីនភាគខាងលិច","Armenia":"ម៉ោង​នៅ​អាមេនី","Atlantic":"ម៉ោង​នៅ​អាត្លង់ទិក","Australia_Central":"ម៉ោង​នៅអូស្ត្រាលី​កណ្ដាល","Australia_CentralWestern":"ម៉ោង​នៅ​​​ភាគ​ខាង​លិច​នៅ​អូស្ត្រាលី​កណ្ដាល","Australia_Eastern":"ម៉ោង​នៅ​អូស្ត្រាលី​ខាង​កើត","Australia_Western":"ម៉ោង​​​នៅ​អូស្ត្រាលី​ខាង​លិច","Azerbaijan":"ម៉ោង​នៅ​អាស៊ែបៃហ្សង់","Azores":"ម៉ោង​នៅ​អេហ្សស","Bangladesh":"ម៉ោង​នៅ​បង់ក្លាដែស","Bhutan":"ម៉ោងនៅប៊ូតង់","Bolivia":"ម៉ោង​នៅ​បូលីវី","Brasilia":"ម៉ោង​នៅ​ប្រាស៊ីលីយ៉ា","Brunei":"ម៉ោងនៅព្រុយណេដារូសាឡឹម","Cape_Verde":"ម៉ោង​នៅ​កាប់វែរ","Chamorro":"ម៉ោង​ស្តង់ដារនៅ​ចាំម៉ូរ៉ូ","Chatham":"ម៉ោង​នៅ​ចាថាំ","Chile":"ម៉ោងនៅស៊ីលី","China":"ម៉ោង​នៅ​ចិន","Choibalsan":"ម៉ោង​នៅ​ឆូបាល់សាន","Christmas":"ម៉ោង​នៅ​កោះ​គ្រីស្មាស","Cocos":"ម៉ោង​នៅ​ប្រជុំកោះ​កូកូស","Colombia":"ម៉ោង​នៅ​កូឡុំប៊ី","Cook":"ម៉ោង​នៅប្រជុំ​កោះ​ខូក","Cuba":"ម៉ោង​នៅ​គុយបា","Davis":"ម៉ោង​នៅ​ដាវីស","DumontDUrville":"ម៉ោង​នៅ​ឌុយម៉ុងដឺអ៊ុយវីល","East_Timor":"ម៉ោង​នៅ​​ទីម័រ​ខាង​កើត","Easter":"ម៉ោងនៅកោះអ៊ីស្ទ័រ","Ecuador":"ម៉ោង​នៅ​អេក្វាទ័រ","Europe_Central":"ម៉ោង​នៅ​អឺរ៉ុប​កណ្ដាល","Europe_Eastern":"ម៉ោង​នៅ​អឺរ៉ុប​​ខាង​កើត​","Europe_Further_Eastern":"ម៉ោង​នៅ​ចុងបូព៌ានៃទ្វីប​អឺរ៉ុប​","Europe_Western":"ម៉ោង​នៅ​អឺរ៉ុប​ខាង​លិច","Falkland":"ម៉ោង​នៅ​ប្រជុំកោះ​ហ្វក់ឡែន","Fiji":"ម៉ោង​នៅ​ហ្វីជី","French_Guiana":"ម៉ោង​នៅ​ហ្គីយ៉ាន​បារាំង","French_Southern":"ម៉ោងនៅបារាំងខាងត្បូង និងនៅអង់តាំងទិក","GMT":"ម៉ោងនៅគ្រីនវិច","Galapagos":"ម៉ោង​នៅ​កាឡាប៉ាកូស","Gambier":"ម៉ោង​នៅ​កាំបៀ","Georgia":"ម៉ោង​នៅ​ហ្សកហ្ស៊ី","Gilbert_Islands":"ម៉ោង​នៅ​កោះ​កីប៊ឺត","Greenland_Eastern":"ម៉ោង​​នៅ​ហ្គ្រីនលែន​ខាង​កើត","Greenland_Western":"ម៉ោងនៅហ្គ្រីនលែនខាងលិច","Gulf":"ម៉ោង​ស្តង់ដា​នៅ​កាល់","Guyana":"ម៉ោង​នៅ​ហ្គីយ៉ាន","Hawaii_Aleutian":"ម៉ោង​​នៅ​ហាវៃ-អាល់ដ្យូសិន","Hong_Kong":"ម៉ោង​នៅ​ហុងកុង","Hovd":"ម៉ោង​នៅ​ហូវ","India":"ម៉ោង​ស្តង់ដារនៅ​ឥណ្ឌា","Indian_Ocean":"ម៉ោង​នៅ​មហាសមុទ្រ​ឥណ្ឌា","Indochina":"ម៉ោង​នៅ​ឥណ្ឌូចិន","Indonesia_Central":"ម៉ោង​នៅ​ឥណ្ឌូណេស៊ី​​​កណ្ដាល","Indonesia_Eastern":"ម៉ោង​នៅ​ឥណ្ឌូណេស៊ី​​ខាង​កើត","Indonesia_Western":"ម៉ោង​នៅ​ឥណ្ឌូណេស៊ី​​ខាង​លិច","Iran":"ម៉ោង​នៅ​អ៊ីរ៉ង់","Irkutsk":"ម៉ោងនៅអៀរគុតស្កិ៍","Israel":"ម៉ោង​នៅ​អ៊ីស្រាអែល","Japan":"ម៉ោង​នៅ​ជប៉ុន","Kazakhstan_Eastern":"ម៉ោង​កាហ្សាក់ស្ថាន​​ខាង​កើត","Kazakhstan_Western":"ម៉ោង​នៅ​កាហ្សាក់ស្ថាន​ខាង​​​លិច","Korea":"ម៉ោង​នៅ​កូរ៉េ","Kosrae":"ម៉ោង​នៅ​កូស្រៃ","Krasnoyarsk":"ម៉ោង​នៅ​ក្រាណូយ៉ាស","Kyrgystan":"ម៉ោងនៅកៀហ្ស៊ីស៊ីស្ថាន","Line_Islands":"ម៉ោង​នៅ​កោះ​ឡាញ","Lord_Howe":"ម៉ោង​នៅ​ឡតហៅ","Macquarie":"ម៉ោង​នៅ​កោះ​ម៉ាកគែរី","Magadan":"ម៉ោង​នៅ​ម៉ាហ្កាដាន","Malaysia":"ម៉ោង​នៅ​ម៉ាឡេស៊ី","Maldives":"ម៉ោង​នៅ​ម៉ាល់ឌីវ","Marquesas":"ម៉ោង​នៅ​កោះ​ម៉ាគឺសាស់","Marshall_Islands":"ម៉ោង​នៅ​ម៉ាសាល","Mauritius":"ម៉ោង​នៅ​ម៉ូរីស","Mawson":"ម៉ោង​នៅ​ម៉ៅ​សាន់","Mexico_Northwest":"ម៉ោង​នៅ​ម៉ិកស៊ិកភាគពាយព្យ","Mexico_Pacific":"ម៉ោង​នៅ​ប៉ាស៊ីហ្វិក​ម៉ិកស៊ិក","Mongolia":"ម៉ោង​នៅ​អ៊ូឡាន​បាទូ","Moscow":"ម៉ោង​នៅ​មូស្គូ","Myanmar":"ម៉ោង​នៅ​មីយ៉ាន់ម៉ា","Nauru":"ម៉ោង​នៅ​ណូរូ","Nepal":"ម៉ោងនៅនេប៉ាល់","New_Caledonia":"ម៉ោង​នៅណូវ៉ែលកាឡេដូនៀ","New_Zealand":"ម៉ោង​នៅ​នូវែលសេឡង់","Newfoundland":"ម៉ោង​​នៅញូវហ្វោនឡែន","Niue":"ម៉ោងនៅ​នីវ៉េ","Norfolk":"ម៉ោង​នៅ​កោះ​ណ័រហ្វក់","Noronha":"ម៉ោង​នៅហ្វ៊ែណាន់ដូ​ដឺណូរ៉ូញ៉ា","Novosibirsk":"ម៉ោង​នៅ​ណូវ៉ូស៊ីប៊ីក","Omsk":"ម៉ោង​នៅ​អូម","Pakistan":"ម៉ោង​នៅ​ប៉ាគីស្ថាន","Palau":"ម៉ោង​នៅ​ផាឡៅ","Papua_New_Guinea":"ម៉ោង​នៅប៉ាពូអាស៊ី នូវែលហ្គីណេ","Paraguay":"ម៉ោង​នៅ​ប៉ារ៉ាហ្គាយ","Peru":"ម៉ោង​នៅ​ប៉េរូ","Philippines":"ម៉ោង​នៅ​ហ្វីលីពីន","Phoenix_Islands":"ម៉ោង​នៅ​កោះ​ផូនីក","Pierre_Miquelon":"ម៉ោង​​​នៅសង់​ព្យែរ និង​មីគុយឡុង","Pitcairn":"ម៉ោង​នៅ​ភីឃឺន","Ponape":"ម៉ោង​នៅ​ប៉ូណាប់","Pyongyang":"ម៉ោងនៅព្យុងយ៉ាង","Reunion":"ម៉ោងនៅរេអ៊ុយ៉ុង","Rothera":"ម៉ោង​នៅ​រ៉ូធឺរ៉ា","Sakhalin":"ម៉ោង​នៅ​សាក់ខាលីន","Samoa":"ម៉ោង​នៅ​សាម័រ","Seychelles":"ម៉ោង​នៅ​សីស្ហែល","Singapore":"ម៉ោង​នៅ​សិង្ហបូរី","Solomon":"ម៉ោង​នៅ​កោះ​សូឡូម៉ុន","South_Georgia":"ម៉ោង​នៅ​កោះ​ហ្សកហ្ស៊ី","Suriname":"ម៉ោង​នៅ​សូរីណាម","Syowa":"ម៉ោង​នៅ​ស៊ីអូវ៉ា","Tahiti":"ម៉ោង​នៅ​តាហិទី","Taipei":"ម៉ោង​នៅ​តៃប៉ិ","Tajikistan":"ម៉ោងនៅតាជីគីស្ថាន","Tokelau":"ម៉ោង​នៅ​តូខេឡៅ","Tonga":"ម៉ោង​នៅ​តុងហ្គា","Truk":"ម៉ោង​នៅ​ចូអុក","Turkmenistan":"ម៉ោង​នៅ​តួកម៉េនីស្ថាន","Tuvalu":"ម៉ោង​នៅ​ទុយវ៉ាលូ","Uruguay":"ម៉ោង​នៅ​អ៊ុយរូហ្គាយ","Uzbekistan":"ម៉ោង​នៅ​អ៊ូសបេគីស្ថាន","Vanuatu":"ម៉ោង​នៅ​វ៉ានូទូ","Venezuela":"ម៉ោង​នៅ​វ៉េណេស៊ុយអេឡា","Vladivostok":"ម៉ោង​នៅ​វ៉្លាឌីវ៉ូស្តុក","Volgograd":"ម៉ោង​នៅ​វ៉ូហ្កោក្រាដ","Vostok":"ម៉ោង​នៅ​វ័រស្តុក","Wake":"ម៉ោង​នៅ​កោះវេក","Wallis":"ម៉ោង​នៅ​វ៉ាលីស និងហ្វ៊ុទូណា","Yakutsk":"ម៉ោង​នៅ​យ៉ាគុតស្កិ៍","Yekaterinburg":"ម៉ោង​នៅ​អ៊ិខាធឺរីនប៊័ក"}
