{"Acre":"Ako laikas","Afghanistan":"Afganistano laikas","Africa_Central":"Centrinės Afrikos laikas","Africa_Eastern":"Rytų Afrikos laikas","Africa_Southern":"Pietų Afrikos laikas","Africa_Western":"Vakarų Afrikos laikas","Alaska":"Aliaskos laikas","Almaty":"Almatos laikas","Amazon":"Amazonės laikas","America_Central":"Šiaurės Amerikos centro laikas","America_Eastern":"Šiaurės Amerikos rytų laikas","America_Mountain":"Šiaurės Amerikos kalnų laikas","America_Pacific":"Šiaurės Amerikos Ramiojo vandenyno laikas","Anadyr":"Anadyrės laikas","Apia":"Apijos laikas","Aqtau":"Aktau laikas","Aqtobe":"Aktobės laikas","Arabian":"Arabijos laikas","Argentina":"Argentinos laikas","Argentina_Western":"Vakarų Argentinos laikas","Armenia":"Armėnijos laikas","Atlantic":"Atlanto laikas","Australia_Central":"Centrinės Australijos laikas","Australia_CentralWestern":"Centrinės vakarų Australijos laikas","Australia_Eastern":"Rytų Australijos laikas","Australia_Western":"Vakarų Australijos laikas","Azerbaijan":"Azerbaidžano laikas","Azores":"Azorų Salų laikas","Bangladesh":"Bangladešo laikas","Bhutan":"Butano laikas","Bolivia":"Bolivijos laikas","Brasilia":"Brazilijos laikas","Brunei":"Brunėjaus Darusalamo laikas","Cape_Verde":"Žaliojo Kyšulio laikas","Casey":"Keisio laikas","Chamorro":"Čamoro laikas","Chatham":"Čatamo laikas","Chile":"Čilės laikas","China":"Kinijos laikas","Choibalsan":"Čoibalsano laikas","Christmas":"Kalėdų Salos laikas","Cocos":"Kokosų Salų laikas","Colombia":"Kolumbijos laikas","Cook":"Kuko Salų laikas","Cuba":"Kubos laikas","Davis":"Deiviso laikas","DumontDUrville":"Diumono d’Urvilio laikas","East_Timor":"Rytų Timoro laikas","Easter":"Velykų Salos laikas","Ecuador":"Ekvadoro laikas","Europe_Central":"Vidurio Europos laikas","Europe_Eastern":"Rytų Europos laikas","Europe_Further_Eastern":"Tolimųjų rytų Europos laikas","Europe_Western":"Vakarų Europos laikas","Falkland":"Folklando Salų laikas","Fiji":"Fidžio laikas","French_Guiana":"Prancūzijos Gvianos laikas","French_Southern":"Pietų Prancūzijos ir antarktinis laikas","GMT":"Grinvičo laikas","Galapagos":"Galapagų laikas","Gambier":"Gambyro laikas","Georgia":"Gruzijos laikas","Gilbert_Islands":"Gilberto Salų laikas","Greenland_Eastern":"Grenlandijos rytų laikas","Greenland_Western":"Grenlandijos vakarų laikas","Guam":"Guamo laikas","Gulf":"Persijos įlankos laikas","Guyana":"Gajanos laikas","Hawaii_Aleutian":"Havajų-Aleutų laikas","Hong_Kong":"Honkongo laikas","Hovd":"Hovdo laikas","India":"Indijos laikas","Indian_Ocean":"Indijos vandenyno laikas","Indochina":"Indokinijos laikas","Indonesia_Central":"Centrinės Indonezijos laikas","Indonesia_Eastern":"Rytų Indonezijos laikas","Indonesia_Western":"Vakarų Indonezijos laikas","Iran":"Irano laikas","Irkutsk":"Irkutsko laikas","Israel":"Izraelio laikas","Japan":"Japonijos laikas","Kamchatka":"Kamčiatkos Petropavlovsko laikas","Kazakhstan_Eastern":"Rytų Kazachstano laikas","Kazakhstan_Western":"Vakarų Kazachstano laikas","Korea":"Korėjos laikas","Kosrae":"Kosrajė laikas","Krasnoyarsk":"Krasnojarsko laikas","Kyrgystan":"Kirgistano laikas","Lanka":"Lankos laikas","Line_Islands":"Laino Salų laikas","Lord_Howe":"Lordo Hau laikas","Macau":"Makau laikas","Macquarie":"Makvorio Salos laikas","Magadan":"Magadano laikas","Malaysia":"Malaizijos laikas","Maldives":"Maldyvų laikas","Marquesas":"Markizo Salų laikas","Marshall_Islands":"Maršalo Salų laikas","Mauritius":"Mauricijaus laikas","Mawson":"Mosono laikas","Mexico_Northwest":"Šiaurės Vakarų Meksikos laikas","Mexico_Pacific":"Meksikos Ramiojo vandenyno laikas","Mongolia":"Ulan Batoro laikas","Moscow":"Maskvos laikas","Myanmar":"Mianmaro laikas","Nauru":"Nauru laikas","Nepal":"Nepalo laikas","New_Caledonia":"Naujosios Kaledonijos laikas","New_Zealand":"Naujosios Zelandijos laikas","Newfoundland":"Niufaundlendo laikas","Niue":"Niujė laikas","Norfolk":"Norfolko Salų laikas","Noronha":"Fernando de Noronjos laikas","North_Mariana":"Šiaurės Marianos Salų laikas","Novosibirsk":"Novosibirsko laikas","Omsk":"Omsko laikas","Pakistan":"Pakistano laikas","Palau":"Palau laikas","Papua_New_Guinea":"Papua Naujosios Gvinėjos laikas","Paraguay":"Paragvajaus laikas","Peru":"Peru laikas","Philippines":"Filipinų laikas","Phoenix_Islands":"Fenikso Salų laikas","Pierre_Miquelon":"Sen Pjero ir Mikelono laikas","Pitcairn":"Pitkerno laikas","Ponape":"Ponapės laikas","Pyongyang":"Pchenjano laikas","Qyzylorda":"Kyzylordos laikas","Reunion":"Reunjono laikas","Rothera":"Roteros laikas","Sakhalin":"Sachalino laikas","Samara":"Samaros laikas","Samoa":"Samoa laikas","Seychelles":"Seišelių laikas","Singapore":"Singapūro laikas","Solomon":"Saliamono Salų laikas","South_Georgia":"Pietų Džordžijos laikas","Suriname":"Surinamo laikas","Syowa":"Siovos laikas","Tahiti":"Tahičio laikas","Taipei":"Taipėjaus laikas","Tajikistan":"Tadžikistano laikas","Tokelau":"Tokelau laikas","Tonga":"Tongos laikas","Truk":"Čuko laikas","Turkmenistan":"Turkmėnistano laikas","Tuvalu":"Tuvalu laikas","Uruguay":"Urugvajaus laikas","Uzbekistan":"Uzbekistano laikas","Vanuatu":"Vanuatu laikas","Venezuela":"Venesuelos laikas","Vladivostok":"Vladivostoko laikas","Volgograd":"Volgogrado laikas","Vostok":"Vostoko laikas","Wake":"Veiko Salos laikas","Wallis":"Voliso ir Futūnos laikas","Yakutsk":"Jakutsko laikas","Yekaterinburg":"Jekaterinburgo laikas"}
