{"Afghanistan":"Афганістанскі час","Africa_Central":"Цэнтральнаафрыканскі час","Africa_Eastern":"Усходнеафрыканскі час","Africa_Southern":"Паўднёваафрыканскі час","Africa_Western":"Заходнеафрыканскі час","Alaska":"Час Аляскі","Amazon":"Амазонскі час","America_Central":"Паўночнаамерыканскі цэнтральны час","America_Eastern":"Паўночнаамерыканскі ўсходні час","America_Mountain":"Паўночнаамерыканскі горны час","America_Pacific":"Ціхаакіянскі час","Apia":"Час Апіі","Arabian":"Час Саудаўскай Аравіі","Argentina":"Аргенцінскі час","Argentina_Western":"Час Заходняй Аргенціны","Armenia":"Час Арменіі","Atlantic":"Атлантычны час","Australia_Central":"Час цэнтральнай Аўстраліі","Australia_CentralWestern":"Цэнтральна-заходні час Аўстраліі","Australia_Eastern":"Час усходняй Аўстраліі","Australia_Western":"Час заходняй Аўстраліі","Azerbaijan":"Час Азербайджана","Azores":"Час Азорскіх астравоў","Bangladesh":"Час Бангладэш","Bhutan":"Час Бутана","Bolivia":"Балівійскі час","Brasilia":"Бразільскі час","Brunei":"Час Брунея","Cape_Verde":"Час Каба-Вердэ","Chamorro":"Час Чамора","Chatham":"Час Чатэма","Chile":"Чылійскі час","China":"Час Кітая","Choibalsan":"Час Чайбалсана","Christmas":"Час вострава Каляд","Cocos":"Час Какосавых астравоў","Colombia":"Калумбійскі час","Cook":"Час астравоў Кука","Cuba":"Час Кубы","Davis":"Час станцыі Дэйвіс","DumontDUrville":"Час станцыі Дзюмон-Дзюрвіль","East_Timor":"Час Усходняга Тымора","Easter":"Час вострава Вялікадня","Ecuador":"Эквадорскі час","Europe_Central":"Цэнтральнаеўрапейскі час","Europe_Eastern":"Усходнееўрапейскі час","Europe_Further_Eastern":"Далёкаўсходнееўрапейскі час","Europe_Western":"Заходнееўрапейскі час","Falkland":"Час Фалклендскіх астравоў","Fiji":"Час Фіджы","French_Guiana":"Час Французскай Гвіяны","French_Southern":"Час Французскай паўднёва-антарктычнай тэрыторыі","GMT":"Час па Грынвічы","Galapagos":"Стандартны час Галапагоскіх астравоў","Gambier":"Час астравоў Гамб’е","Georgia":"Грузінскі час","Gilbert_Islands":"Час астравоў Гілберта","Greenland_Eastern":"Час Усходняй Грэнландыі","Greenland_Western":"Час Заходняй Грэнландыі","Gulf":"Час Персідскага заліва","Guyana":"Час Гаяны","Hawaii_Aleutian":"Гавайска-Алеуцкі час","Hong_Kong":"Час Ганконга","Hovd":"Час Хоўда","India":"Час Індыі","Indian_Ocean":"Час Індыйскага акіяна","Indochina":"Індакітайскі час","Indonesia_Central":"Цэнтральнаінданезійскі час","Indonesia_Eastern":"Усходнеінданезійскі час","Indonesia_Western":"Заходнеінданезійскі час","Iran":"Іранскі час","Irkutsk":"Іркуцкі час","Israel":"Ізраільскі час","Japan":"Час Японіі","Kazakhstan_Eastern":"Усходнеказахстанскі час","Kazakhstan_Western":"Заходнеказахстанскі час","Korea":"Час Карэі","Kosrae":"Час астравоў Кусаіе","Krasnoyarsk":"Краснаярскі час","Kyrgystan":"Час Кыргызстана","Line_Islands":"Час астравоў Лайн","Lord_Howe":"Час Лорд-Хау","Macquarie":"Час вострава Макуоры","Magadan":"Магаданскі час","Malaysia":"Час Малайзіі","Maldives":"Час Мальдываў","Marquesas":"Час Маркізскіх астравоў","Marshall_Islands":"Час Маршалавых астравоў","Mauritius":"Час Маўрыкія","Mawson":"Час станцыі Моўсан","Mexico_Northwest":"Паўночна-заходні мексіканскі час","Mexico_Pacific":"Мексіканскі ціхаакіянскі час","Mongolia":"Час Улан-Батара","Moscow":"Маскоўскі час","Myanmar":"Час М’янмы","Nauru":"Час Науру","Nepal":"Непальскі час","New_Caledonia":"Час Новай Каледоніі","New_Zealand":"Час Новай Зеландыі","Newfoundland":"Ньюфаўндлендскі час","Niue":"Час Ніуэ","Norfolk":"Час вострава Норфалк","Noronha":"Час Фернанду-дзі-Наронья","Novosibirsk":"Новасібірскі час","Omsk":"Омскі час","Pakistan":"Пакістанскі час","Palau":"Час Палау","Papua_New_Guinea":"Час Папуа-Новай Гвінеі","Paraguay":"Час Парагвая","Peru":"Перуанскі час","Philippines":"Філіпінскі час","Phoenix_Islands":"Час астравоў Фенікс","Pierre_Miquelon":"Час Сен-П’ер і Мікелон","Pitcairn":"Час вострава Піткэрн","Ponape":"Час вострава Панпеі","Pyongyang":"Пхеньянскі час","Reunion":"Час Рэюньёна","Rothera":"Час станцыі Ротэра","Sakhalin":"Сахалінскі час","Samoa":"Час Самоа","Seychelles":"Час Сейшэльскіх астравоў","Singapore":"Сінгапурскі час","Solomon":"Час Саламонавых астравоў","South_Georgia":"Час Паўднёвай Георгіі","Suriname":"Час Сурынама","Syowa":"Час станцыі Сёва","Tahiti":"Час Таіці","Taipei":"Час Тайбэя","Tajikistan":"Час Таджыкістана","Tokelau":"Час Такелау","Tonga":"Час Тонга","Truk":"Час Трука","Turkmenistan":"Час Туркменістана","Tuvalu":"Час Тувалу","Uruguay":"Уругвайскі час","Uzbekistan":"Час Узбекістана","Vanuatu":"Час Вануату","Venezuela":"Венесуэльскі час","Vladivostok":"Уладзівастоцкі час","Volgograd":"Валгаградскі час","Vostok":"Час станцыі Васток","Wake":"Час вострава Уэйк","Wallis":"Час астравоў Уоліс і Футуна","Yakutsk":"Якуцкі час","Yekaterinburg":"Екацярынбургскі час"}
