{"Acre":"Acrejský čas","Afghanistan":"Afghánský čas","Africa_Central":"Středoafrický čas","Africa_Eastern":"Východoafrický čas","Africa_Southern":"Jihoafrický čas","Africa_Western":"Západoafrický čas","Alaska":"Aljašský čas","Almaty":"Almatský čas","Amazon":"Amazonský čas","America_Central":"Severoamerický centrální čas","America_Eastern":"Severoamerický východní čas","America_Mountain":"Severoamerický horský čas","America_Pacific":"Severoamerický pacifický čas","Anadyr":"Anadyrský čas","Apia":"Apijský čas","Aqtau":"Aktauský čas","Aqtobe":"Aktobský čas","Arabian":"Arabský čas","Argentina":"Argentinský čas","Argentina_Western":"Západoargentinský čas","Armenia":"Arménský čas","Atlantic":"Atlantický čas","Australia_Central":"Středoaustralský čas","Australia_CentralWestern":"Středozápadní australský čas","Australia_Eastern":"Východoaustralský čas","Australia_Western":"Západoaustralský čas","Azerbaijan":"Ázerbájdžánský čas","Azores":"Azorský čas","Bangladesh":"Bangladéšský čas","Bhutan":"Bhútánský čas","Bolivia":"Bolivijský čas","Brasilia":"Brasilijský čas","Brunei":"Brunejský čas","Cape_Verde":"Kapverdský čas","Casey":"Čas Caseyho stanice","Chamorro":"Chamorrský čas","Chatham":"Chathamský čas","Chile":"Chilský čas","China":"Čínský čas","Choibalsan":"Čojbalsanský čas","Christmas":"Čas Vánočního ostrova","Cocos":"Čas Kokosových ostrovů","Colombia":"Kolumbijský čas","Cook":"Čas Cookových ostrovů","Cuba":"Kubánský čas","Davis":"Čas Davisovy stanice","DumontDUrville":"Čas stanice Dumonta d’Urvilla","East_Timor":"Východotimorský čas","Easter":"Čas Velikonočního ostrova","Ecuador":"Ekvádorský čas","Europe_Central":"Středoevropský čas","Europe_Eastern":"Východoevropský čas","Europe_Further_Eastern":"Dálněvýchodoevropský čas","Europe_Western":"Západoevropský čas","Falkland":"Falklandský čas","Fiji":"Fidžijský čas","French_Guiana":"Francouzskoguyanský čas","French_Southern":"Čas Francouzských jižních a antarktických území","GMT":"Greenwichský střední čas","Galapagos":"Galapážský čas","Gambier":"Gambierský čas","Georgia":"Gruzínský čas","Gilbert_Islands":"Čas Gilbertových ostrovů","Greenland_Eastern":"Východogrónský čas","Greenland_Western":"Západogrónský čas","Guam":"Guamský čas","Gulf":"Standardní čas Perského zálivu","Guyana":"Guyanský čas","Hawaii_Aleutian":"Havajsko-aleutský čas","Hong_Kong":"Hongkongský čas","Hovd":"Hovdský čas","India":"Indický čas","Indian_Ocean":"Indickooceánský čas","Indochina":"Indočínský čas","Indonesia_Central":"Středoindonéský čas","Indonesia_Eastern":"Východoindonéský čas","Indonesia_Western":"Západoindonéský čas","Iran":"Íránský čas","Irkutsk":"Irkutský čas","Israel":"Izraelský čas","Japan":"Japonský čas","Kamchatka":"Petropavlovsko-kamčatský čas","Kazakhstan_Eastern":"Východokazachstánský čas","Kazakhstan_Western":"Západokazachstánský čas","Korea":"Korejský čas","Kosrae":"Kosrajský čas","Krasnoyarsk":"Krasnojarský čas","Kyrgystan":"Kyrgyzský čas","Lanka":"Srílanský čas","Line_Islands":"Čas Rovníkových ostrovů","Lord_Howe":"Čas ostrova lorda Howa","Macau":"Macajský čas","Macquarie":"Čas ostrova Macquarie","Magadan":"Magadanský čas","Malaysia":"Malajský čas","Maldives":"Maledivský čas","Marquesas":"Markézský čas","Marshall_Islands":"Čas Marshallových ostrovů","Mauritius":"Mauricijský čas","Mawson":"Čas Mawsonovy stanice","Mexico_Northwest":"Severozápadní mexický čas","Mexico_Pacific":"Mexický pacifický čas","Mongolia":"Ulánbátarský čas","Moscow":"Moskevský čas","Myanmar":"Myanmarský čas","Nauru":"Naurský čas","Nepal":"Nepálský čas","New_Caledonia":"Novokaledonský čas","New_Zealand":"Novozélandský čas","Newfoundland":"Newfoundlandský čas","Niue":"Niuejský čas","Norfolk":"Norfolkský čas","Noronha":"Čas souostroví Fernando de Noronha","North_Mariana":"Severomariánský čas","Novosibirsk":"Novosibirský čas","Omsk":"Omský čas","Pakistan":"Pákistánský čas","Palau":"Palauský čas","Papua_New_Guinea":"Čas Papuy-Nové Guiney","Paraguay":"Paraguayský čas","Peru":"Peruánský čas","Philippines":"Filipínský čas","Phoenix_Islands":"Čas Fénixových ostrovů","Pierre_Miquelon":"Pierre-miquelonský čas","Pitcairn":"Čas Pitcairnových ostrovů","Ponape":"Ponapský čas","Pyongyang":"Pchjongjangský čas","Qyzylorda":"Kyzylordský čas","Reunion":"Réunionský čas","Rothera":"Čas Rotherovy stanice","Sakhalin":"Sachalinský čas","Samara":"Samarský čas","Samoa":"Samojský čas","Seychelles":"Seychelský čas","Singapore":"Singapurský čas","Solomon":"Čas Šalamounových ostrovů","South_Georgia":"Čas Jižní Georgie","Suriname":"Surinamský čas","Syowa":"Čas stanice Šówa","Tahiti":"Tahitský čas","Taipei":"Tchajpejský čas","Tajikistan":"Tádžický čas","Tokelau":"Tokelauský čas","Tonga":"Tonžský čas","Truk":"Chuukský čas","Turkmenistan":"Turkmenský čas","Tuvalu":"Tuvalský čas","Uruguay":"Uruguayský čas","Uzbekistan":"Uzbecký čas","Vanuatu":"Vanuatský čas","Venezuela":"Venezuelský čas","Vladivostok":"Vladivostocký čas","Volgograd":"Volgogradský čas","Vostok":"Čas stanice Vostok","Wake":"Čas ostrova Wake","Wallis":"Čas ostrovů Wallis a Futuna","Yakutsk":"Jakutský čas","Yekaterinburg":"Jekatěrinburský čas"}
